{
  "ownerEmail": "admin@tcioe.edu.np",
  "ownerName": "TCIOE Status Admin",
  "ownerPassword": "ChangeMe123!",
  "days": 30,
  "checkIntervalMinutes": 60,
  "resetExisting": true,
  "sites": [
    {
      "url": "https://tcioe.edu.np",
      "site_name": "Main Campus Website",
      "is_public": true,
      "base_ping": 145,
      "uptime": 99.9,
      "ssl_days": 240
    },
    {
      "url": "https://doece.tcioe.edu.np",
      "site_name": "DOECE",
      "is_public": true,
      "base_ping": 165,
      "uptime": 99.5,
      "ssl_days": 130
    },
    {
      "url": "https://doie.tcioe.edu.np",
      "site_name": "DOIE",
      "is_public": true,
      "base_ping": 170,
      "uptime": 99.4,
      "ssl_days": 122
    },
    {
      "url": "https://doas.tcioe.edu.np",
      "site_name": "DOAS",
      "is_public": true,
      "base_ping": 175,
      "uptime": 99.3,
      "ssl_days": 90
    },
    {
      "url": "https://doce.tcioe.edu.np",
      "site_name": "DOCE",
      "is_public": true,
      "base_ping": 178,
      "uptime": 99.3,
      "ssl_days": 84
    },
    {
      "url": "https://doarch.tcioe.edu.np",
      "site_name": "DOARCH",
      "is_public": true,
      "base_ping": 180,
      "uptime": 99.2,
      "ssl_days": 78
    },
    {
      "url": "https://emis.tcioe.edu.np",
      "site_name": "EMIS",
      "is_public": true,
      "base_ping": 135,
      "uptime": 99.95,
      "ssl_days": 265
    },
    {
      "url": "https://admission.tcioe.edu.np",
      "site_name": "Admissions Portal",
      "is_public": true,
      "base_ping": 160,
      "uptime": 99.8,
      "ssl_days": 210
    },
    {
      "url": "https://journal.tcioe.edu.np",
      "site_name": "Journal",
      "is_public": true,
      "base_ping": 195,
      "uptime": 99.1,
      "ssl_days": 64
    },
    {
      "url": "https://ecast.tcioe.edu.np",
      "site_name": "ECAST",
      "is_public": true,
      "base_ping": 205,
      "uptime": 98.9,
      "ssl_days": 57
    },
    {
      "url": "https://rac.tcioe.edu.np",
      "site_name": "RAC",
      "is_public": true,
      "base_ping": 210,
      "uptime": 98.8,
      "ssl_days": 52
    },
    {
      "url": "https://tensor.tcioe.edu.np",
      "site_name": "Tensor",
      "is_public": true,
      "base_ping": 230,
      "uptime": 98.7,
      "ssl_days": 46
    },
    {
      "url": "https://ntbs.tcioe.edu.np",
      "site_name": "NTBS",
      "is_public": true,
      "base_ping": 240,
      "uptime": 98.6,
      "ssl_days": 40
    },
    {
      "url": "https://status.tcioe.edu.np",
      "site_name": "Status",
      "is_public": true,
      "base_ping": 120,
      "uptime": 99.97,
      "ssl_days": 280
    },
    {
      "url": "https://routine.tcioe.edu.np",
      "site_name": "Routine",
      "is_public": true,
      "base_ping": 150,
      "uptime": 99.7,
      "ssl_days": 168
    },
    {
      "url": "https://library.tcioe.edu.np",
      "site_name": "Library",
      "is_public": true,
      "base_ping": 185,
      "uptime": 99.2,
      "ssl_days": 72
    },
    {
      "url": "https://elibrary.tcioe.edu.np",
      "site_name": "eLibrary",
      "is_public": true,
      "base_ping": 190,
      "uptime": 99.0,
      "ssl_days": 61
    }
  ]
}
